django_gen/__init__.py
django_gen/cli.py
django_gen/generator.py
django_gen/scripts/__init__.py
django_gen/scripts/files.py
django_gen/scripts/rewriting.py
django_gen/scripts/write.py
django_gen/templates/__init__.py
django_gen/templates/apps.py
django_gen/templates/base_files.py
django_gen/templates/docker.py
django_gen/templates/settings.py
django_gen/templates/tools.py
django_gen/templates/urls.py
django_gen-0.2.dist-info/LICENSE
django_gen-0.2.dist-info/METADATA
django_gen-0.2.dist-info/WHEEL
django_gen-0.2.dist-info/entry_points.txt
django_gen-0.2.dist-info/top_level.txt
django_gen-0.2.dist-info/RECORD
