Metadata-Version: 2.2
Name: django-gen
Version: 0.2
Summary: 🚀 **Django Project Generator** - bu interaktiv CLI vositasi bo‘lib, u yangi Django loyihalarini tez va soddalashtirilgan
Home-page: https://github.com/zohidillo/django-project-generator
Author: Zohidillo Turgunov
Classifier: Programming Language :: Python :: 3
Classifier: Framework :: Django
License-File: LICENSE
Requires-Dist: django
Requires-Dist: click
Requires-Dist: rich
Dynamic: author
Dynamic: classifier
Dynamic: description
Dynamic: description-content-type
Dynamic: home-page
Dynamic: requires-dist
Dynamic: summary
